{
  "update_time": "2026-06-27 08:13",
  "total": 177,
  "top_gainers": [
    {
      "code": "300162",
      "name": "雷曼光电",
      "pct_chg": 19.98
    },
    {
      "code": "300540",
      "name": "蜀道装备",
      "pct_chg": 19.98
    },
    {
      "code": "300668",
      "name": "杰恩股份",
      "pct_chg": 15.66
    },
    {
      "code": "300260",
      "name": "新莱应材",
      "pct_chg": 14.54
    },
    {
      "code": "300749",
      "name": "顶固集创",
      "pct_chg": 14.21
    },
    {
      "code": "300088",
      "name": "长信科技",
      "pct_chg": 13.41
    },
    {
      "code": "300592",
      "name": "华凯易佰",
      "pct_chg": 12.94
    },
    {
      "code": "300762",
      "name": "上海瀚讯",
      "pct_chg": 11.89
    },
    {
      "code": "300720",
      "name": "海川智能",
      "pct_chg": 10.41
    },
    {
      "code": "002129",
      "name": "TCL中环",
      "pct_chg": 10.03
    },
    {
      "code": "603903",
      "name": "中持股份",
      "pct_chg": 10.03
    },
    {
      "code": "002119",
      "name": "康强电子",
      "pct_chg": 10.02
    },
    {
      "code": "600962",
      "name": "国投中鲁",
      "pct_chg": 10.02
    },
    {
      "code": "605366",
      "name": "宏柏新材",
      "pct_chg": 10.02
    },
    {
      "code": "000823",
      "name": "超声电子",
      "pct_chg": 10.01
    }
  ],
  "top_sectors": [],
  "stocks": [
    {
      "code": "000012",
      "name": "南玻A",
      "pct_chg": 0.63,
      "price": 4.8,
      "prev_high": 4.77,
      "prev_high_date": "2026-06-25",
      "turnover": 7.82
    },
    {
      "code": "000021",
      "name": "深科技",
      "pct_chg": 0.58,
      "price": 53.51,
      "prev_high": 53.2,
      "prev_high_date": "2026-06-25",
      "turnover": 14.44
    },
    {
      "code": "000056",
      "name": "*ST皇庭",
      "pct_chg": 5.08,
      "price": 2.07,
      "prev_high": 1.97,
      "prev_high_date": "2026-06-25",
      "turnover": 3.11
    },
    {
      "code": "000100",
      "name": "TCL科技",
      "pct_chg": 1.12,
      "price": 5.4,
      "prev_high": 5.34,
      "prev_high_date": "2026-06-25",
      "turnover": 12.76
    },
    {
      "code": "000551",
      "name": "创元科技",
      "pct_chg": 6.23,
      "price": 18.25,
      "prev_high": 17.18,
      "prev_high_date": "2026-06-25",
      "turnover": 13.82
    },
    {
      "code": "000620",
      "name": "盈新发展",
      "pct_chg": 9.97,
      "price": 3.42,
      "prev_high": 3.21,
      "prev_high_date": "2026-06-09",
      "turnover": 16.96
    },
    {
      "code": "000703",
      "name": "恒逸石化",
      "pct_chg": 7.34,
      "price": 16.67,
      "prev_high": 15.53,
      "prev_high_date": "2026-06-25",
      "turnover": 6.53
    },
    {
      "code": "000725",
      "name": "京东方A",
      "pct_chg": 3.59,
      "price": 7.79,
      "prev_high": 7.52,
      "prev_high_date": "2026-06-25",
      "turnover": 12.8
    },
    {
      "code": "000728",
      "name": "国元证券",
      "pct_chg": 1.05,
      "price": 7.66,
      "prev_high": 7.58,
      "prev_high_date": "2026-06-25",
      "turnover": 3.04
    },
    {
      "code": "000823",
      "name": "超声电子",
      "pct_chg": 10.01,
      "price": 28.46,
      "prev_high": 25.87,
      "prev_high_date": "2026-06-25",
      "turnover": 17.86
    },
    {
      "code": "000925",
      "name": "众合科技",
      "pct_chg": 3.59,
      "price": 9.52,
      "prev_high": 9.19,
      "prev_high_date": "2026-06-25",
      "turnover": 16.2
    },
    {
      "code": "000962",
      "name": "东方钽业",
      "pct_chg": 3.58,
      "price": 87.03,
      "prev_high": 84.02,
      "prev_high_date": "2026-06-25",
      "turnover": 8.51
    },
    {
      "code": "001229",
      "name": "魅视科技",
      "pct_chg": 3.2,
      "price": 30.02,
      "prev_high": 29.09,
      "prev_high_date": "2026-06-25",
      "turnover": 9.65
    },
    {
      "code": "001309",
      "name": "德明利",
      "pct_chg": 6.73,
      "price": 951.0,
      "prev_high": 891.0,
      "prev_high_date": "2026-06-25",
      "turnover": 13.26
    },
    {
      "code": "001359",
      "name": "平安电工",
      "pct_chg": 1.85,
      "price": 129.93,
      "prev_high": 129.03,
      "prev_high_date": "2026-06-24",
      "turnover": 10.16
    },
    {
      "code": "001389",
      "name": "广合科技",
      "pct_chg": 10.0,
      "price": 220.88,
      "prev_high": 205.8,
      "prev_high_date": "2026-06-17",
      "turnover": 12.87
    },
    {
      "code": "002056",
      "name": "横店东磁",
      "pct_chg": 1.06,
      "price": 30.52,
      "prev_high": 30.2,
      "prev_high_date": "2026-06-25",
      "turnover": 7.34
    },
    {
      "code": "002080",
      "name": "中材科技",
      "pct_chg": 5.1,
      "price": 97.67,
      "prev_high": 92.93,
      "prev_high_date": "2026-06-25",
      "turnover": 5.32
    },
    {
      "code": "002101",
      "name": "广东鸿图",
      "pct_chg": 1.09,
      "price": 9.28,
      "prev_high": 9.23,
      "prev_high_date": "2026-05-26",
      "turnover": 1.87
    },
    {
      "code": "002106",
      "name": "莱宝高科",
      "pct_chg": 10.0,
      "price": 15.62,
      "prev_high": 15.15,
      "prev_high_date": "2026-06-22",
      "turnover": 8.02
    },
    {
      "code": "002119",
      "name": "康强电子",
      "pct_chg": 10.02,
      "price": 37.02,
      "prev_high": 34.51,
      "prev_high_date": "2026-06-18",
      "turnover": 23.14
    },
    {
      "code": "002129",
      "name": "TCL中环",
      "pct_chg": 10.03,
      "price": 11.19,
      "prev_high": 10.71,
      "prev_high_date": "2026-06-17",
      "turnover": 12.85
    },
    {
      "code": "002137",
      "name": "实益达",
      "pct_chg": 2.9,
      "price": 11.02,
      "prev_high": 10.95,
      "prev_high_date": "2026-06-22",
      "turnover": 23.76
    },
    {
      "code": "002141",
      "name": "贤丰控股",
      "pct_chg": 9.92,
      "price": 5.76,
      "prev_high": 5.24,
      "prev_high_date": "2026-06-25",
      "turnover": 24.42
    },
    {
      "code": "002185",
      "name": "华天科技",
      "pct_chg": 0.71,
      "price": 22.56,
      "prev_high": 22.4,
      "prev_high_date": "2026-06-25",
      "turnover": 19.84
    },
    {
      "code": "002225",
      "name": "濮耐股份",
      "pct_chg": 6.94,
      "price": 4.62,
      "prev_high": 4.58,
      "prev_high_date": "2026-06-09",
      "turnover": 14.61
    },
    {
      "code": "002335",
      "name": "科华数据",
      "pct_chg": 3.24,
      "price": 43.62,
      "prev_high": 42.25,
      "prev_high_date": "2026-06-25",
      "turnover": 14.81
    },
    {
      "code": "002371",
      "name": "北方华创",
      "pct_chg": 1.93,
      "price": 813.37,
      "prev_high": 798.0,
      "prev_high_date": "2026-06-25",
      "turnover": 1.71
    },
    {
      "code": "002409",
      "name": "雅克科技",
      "pct_chg": 4.18,
      "price": 188.6,
      "prev_high": 181.03,
      "prev_high_date": "2026-06-25",
      "turnover": 11.18
    },
    {
      "code": "002427",
      "name": "尤夫股份",
      "pct_chg": 4.72,
      "price": 4.88,
      "prev_high": 4.77,
      "prev_high_date": "2026-06-01",
      "turnover": 5.77
    },
    {
      "code": "002430",
      "name": "杭氧股份",
      "pct_chg": 1.22,
      "price": 29.01,
      "prev_high": 28.66,
      "prev_high_date": "2026-06-25",
      "turnover": 3.97
    },
    {
      "code": "002559",
      "name": "亚威股份",
      "pct_chg": 10.01,
      "price": 12.31,
      "prev_high": 11.19,
      "prev_high_date": "2026-06-25",
      "turnover": 21.89
    },
    {
      "code": "002579",
      "name": "中京电子",
      "pct_chg": 6.95,
      "price": 22.78,
      "prev_high": 21.3,
      "prev_high_date": "2026-06-25",
      "turnover": 38.28
    },
    {
      "code": "002587",
      "name": "奥拓电子",
      "pct_chg": 5.92,
      "price": 7.33,
      "prev_high": 7.23,
      "prev_high_date": "2026-05-28",
      "turnover": 15.59
    },
    {
      "code": "002631",
      "name": "德尔未来",
      "pct_chg": 1.23,
      "price": 9.89,
      "prev_high": 9.89,
      "prev_high_date": "2026-06-24",
      "turnover": 8.07
    },
    {
      "code": "002635",
      "name": "安洁科技",
      "pct_chg": 6.02,
      "price": 19.55,
      "prev_high": 18.45,
      "prev_high_date": "2026-06-16",
      "turnover": 16.82
    },
    {
      "code": "002655",
      "name": "共达电声",
      "pct_chg": 5.58,
      "price": 51.13,
      "prev_high": 50.2,
      "prev_high_date": "2026-06-24",
      "turnover": 10.42
    },
    {
      "code": "002668",
      "name": "TCL智家",
      "pct_chg": 7.0,
      "price": 11.0,
      "prev_high": 10.5,
      "prev_high_date": "2026-06-23",
      "turnover": 4.96
    },
    {
      "code": "002674",
      "name": "兴业科技",
      "pct_chg": 10.0,
      "price": 28.83,
      "prev_high": 26.21,
      "prev_high_date": "2026-06-25",
      "turnover": 2.57
    },
    {
      "code": "002745",
      "name": "木林森",
      "pct_chg": 0.87,
      "price": 12.78,
      "prev_high": 12.67,
      "prev_high_date": "2026-06-25",
      "turnover": 11.68
    },
    {
      "code": "002787",
      "name": "华源控股",
      "pct_chg": 7.02,
      "price": 32.47,
      "prev_high": 30.42,
      "prev_high_date": "2026-06-04",
      "turnover": 17.08
    },
    {
      "code": "002821",
      "name": "凯莱英",
      "pct_chg": 1.56,
      "price": 152.5,
      "prev_high": 150.16,
      "prev_high_date": "2026-06-25",
      "turnover": 4.37
    },
    {
      "code": "002859",
      "name": "洁美科技",
      "pct_chg": 6.87,
      "price": 103.77,
      "prev_high": 102.5,
      "prev_high_date": "2026-06-22",
      "turnover": 8.34
    },
    {
      "code": "002861",
      "name": "瀛通通讯",
      "pct_chg": 2.36,
      "price": 22.15,
      "prev_high": 21.64,
      "prev_high_date": "2026-06-25",
      "turnover": 6.84
    },
    {
      "code": "002925",
      "name": "盈趣科技",
      "pct_chg": 1.63,
      "price": 25.0,
      "prev_high": 24.6,
      "prev_high_date": "2026-06-25",
      "turnover": 4.71
    },
    {
      "code": "002937",
      "name": "兴瑞科技",
      "pct_chg": 5.83,
      "price": 45.42,
      "prev_high": 43.13,
      "prev_high_date": "2026-06-24",
      "turnover": 5.77
    },
    {
      "code": "002963",
      "name": "豪尔赛",
      "pct_chg": 0.04,
      "price": 23.01,
      "prev_high": 23.0,
      "prev_high_date": "2026-06-25",
      "turnover": 6.79
    },
    {
      "code": "002965",
      "name": "祥鑫科技",
      "pct_chg": 10.01,
      "price": 51.88,
      "prev_high": 47.16,
      "prev_high_date": "2026-06-25",
      "turnover": 12.12
    },
    {
      "code": "002990",
      "name": "盛视科技",
      "pct_chg": 3.58,
      "price": 75.2,
      "prev_high": 72.6,
      "prev_high_date": "2026-06-25",
      "turnover": 19.87
    },
    {
      "code": "300005",
      "name": "探路者",
      "pct_chg": 1.93,
      "price": 23.21,
      "prev_high": 22.77,
      "prev_high_date": "2026-06-25",
      "turnover": 8.83
    },
    {
      "code": "300052",
      "name": "中青宝",
      "pct_chg": 2.17,
      "price": 14.1,
      "prev_high": 13.8,
      "prev_high_date": "2026-06-25",
      "turnover": 17.86
    },
    {
      "code": "300088",
      "name": "长信科技",
      "pct_chg": 13.41,
      "price": 11.67,
      "prev_high": 10.57,
      "prev_high_date": "2026-06-17",
      "turnover": 24.88
    },
    {
      "code": "300093",
      "name": "金刚光伏",
      "pct_chg": 5.18,
      "price": 25.97,
      "prev_high": 24.69,
      "prev_high_date": "2026-06-25",
      "turnover": 8.92
    },
    {
      "code": "300136",
      "name": "信维通信",
      "pct_chg": 1.25,
      "price": 118.19,
      "prev_high": 116.73,
      "prev_high_date": "2026-06-25",
      "turnover": 14.23
    },
    {
      "code": "300162",
      "name": "雷曼光电",
      "pct_chg": 19.98,
      "price": 12.13,
      "prev_high": 11.95,
      "prev_high_date": "2026-06-22",
      "turnover": 30.61
    },
    {
      "code": "300196",
      "name": "长海股份",
      "pct_chg": 3.06,
      "price": 32.99,
      "prev_high": 32.99,
      "prev_high_date": "2026-06-22",
      "turnover": 20.25
    },
    {
      "code": "300200",
      "name": "高盟新材",
      "pct_chg": 3.94,
      "price": 11.87,
      "prev_high": 11.42,
      "prev_high_date": "2026-06-25",
      "turnover": 13.35
    },
    {
      "code": "300214",
      "name": "日科化学",
      "pct_chg": 4.49,
      "price": 10.25,
      "prev_high": 10.21,
      "prev_high_date": "2026-06-22",
      "turnover": 6.42
    },
    {
      "code": "300219",
      "name": "鸿利智汇",
      "pct_chg": 5.24,
      "price": 10.05,
      "prev_high": 9.55,
      "prev_high_date": "2026-06-25",
      "turnover": 14.19
    },
    {
      "code": "300236",
      "name": "上海新阳",
      "pct_chg": 2.8,
      "price": 116.76,
      "prev_high": 114.41,
      "prev_high_date": "2026-06-24",
      "turnover": 7.38
    },
    {
      "code": "300260",
      "name": "新莱应材",
      "pct_chg": 14.54,
      "price": 92.9,
      "prev_high": 83.85,
      "prev_high_date": "2026-06-24",
      "turnover": 17.68
    },
    {
      "code": "300285",
      "name": "国瓷材料",
      "pct_chg": 4.48,
      "price": 102.81,
      "prev_high": 98.9,
      "prev_high_date": "2026-06-22",
      "turnover": 16.55
    },
    {
      "code": "300301",
      "name": "ST长方",
      "pct_chg": 6.0,
      "price": 3.71,
      "prev_high": 3.63,
      "prev_high_date": "2026-06-24",
      "turnover": 3.49
    },
    {
      "code": "300316",
      "name": "晶盛机电",
      "pct_chg": 3.35,
      "price": 58.37,
      "prev_high": 57.3,
      "prev_high_date": "2026-06-22",
      "turnover": 4.25
    },
    {
      "code": "300321",
      "name": "同大股份",
      "pct_chg": 8.8,
      "price": 57.61,
      "prev_high": 54.3,
      "prev_high_date": "2026-06-22",
      "turnover": 11.49
    },
    {
      "code": "300323",
      "name": "华灿光电",
      "pct_chg": 5.68,
      "price": 19.36,
      "prev_high": 18.32,
      "prev_high_date": "2026-06-25",
      "turnover": 21.56
    },
    {
      "code": "300346",
      "name": "南大光电",
      "pct_chg": 4.55,
      "price": 78.12,
      "prev_high": 77.0,
      "prev_high_date": "2026-06-24",
      "turnover": 16.94
    },
    {
      "code": "300347",
      "name": "泰格医药",
      "pct_chg": 2.71,
      "price": 45.05,
      "prev_high": 43.86,
      "prev_high_date": "2026-06-25",
      "turnover": 4.9
    },
    {
      "code": "300382",
      "name": "斯莱克",
      "pct_chg": 9.24,
      "price": 20.81,
      "prev_high": 19.05,
      "prev_high_date": "2026-06-25",
      "turnover": 10.49
    },
    {
      "code": "300398",
      "name": "飞凯材料",
      "pct_chg": 8.17,
      "price": 61.29,
      "prev_high": 56.66,
      "prev_high_date": "2026-06-25",
      "turnover": 20.04
    },
    {
      "code": "300401",
      "name": "花园生物",
      "pct_chg": 1.86,
      "price": 22.51,
      "prev_high": 22.1,
      "prev_high_date": "2026-06-25",
      "turnover": 12.6
    },
    {
      "code": "300416",
      "name": "苏试试验",
      "pct_chg": 1.9,
      "price": 20.38,
      "prev_high": 20.17,
      "prev_high_date": "2026-06-24",
      "turnover": 6.95
    },
    {
      "code": "300420",
      "name": "五洋自控",
      "pct_chg": 7.56,
      "price": 9.68,
      "prev_high": 9.0,
      "prev_high_date": "2026-06-25",
      "turnover": 19.73
    },
    {
      "code": "300440",
      "name": "运达科技",
      "pct_chg": 6.22,
      "price": 21.36,
      "prev_high": 20.72,
      "prev_high_date": "2026-06-24",
      "turnover": 4.95
    },
    {
      "code": "300446",
      "name": "航天智造",
      "pct_chg": 5.26,
      "price": 17.42,
      "prev_high": 17.0,
      "prev_high_date": "2026-05-26",
      "turnover": 9.76
    },
    {
      "code": "300480",
      "name": "光力科技",
      "pct_chg": 4.06,
      "price": 39.73,
      "prev_high": 38.5,
      "prev_high_date": "2026-06-24",
      "turnover": 17.25
    },
    {
      "code": "300506",
      "name": "名家汇",
      "pct_chg": 6.1,
      "price": 6.26,
      "prev_high": 5.9,
      "prev_high_date": "2026-06-25",
      "turnover": 9.12
    },
    {
      "code": "300537",
      "name": "广信材料",
      "pct_chg": 5.14,
      "price": 32.52,
      "prev_high": 32.46,
      "prev_high_date": "2026-06-24",
      "turnover": 24.88
    },
    {
      "code": "300540",
      "name": "蜀道装备",
      "pct_chg": 19.98,
      "price": 30.5,
      "prev_high": 29.28,
      "prev_high_date": "2026-06-11",
      "turnover": 17.73
    },
    {
      "code": "300545",
      "name": "联得装备",
      "pct_chg": 3.78,
      "price": 39.28,
      "prev_high": 38.38,
      "prev_high_date": "2026-06-22",
      "turnover": 20.42
    },
    {
      "code": "300567",
      "name": "精测电子",
      "pct_chg": 4.56,
      "price": 275.0,
      "prev_high": 263.0,
      "prev_high_date": "2026-06-25",
      "turnover": 6.31
    },
    {
      "code": "300592",
      "name": "华凯易佰",
      "pct_chg": 12.94,
      "price": 16.93,
      "prev_high": 15.46,
      "prev_high_date": "2026-06-24",
      "turnover": 8.54
    },
    {
      "code": "300602",
      "name": "飞荣达",
      "pct_chg": 0.79,
      "price": 49.97,
      "prev_high": 49.58,
      "prev_high_date": "2026-06-25",
      "turnover": 9.8
    },
    {
      "code": "300604",
      "name": "长川科技",
      "pct_chg": 1.58,
      "price": 314.9,
      "prev_high": 309.99,
      "prev_high_date": "2026-06-25",
      "turnover": 7.18
    },
    {
      "code": "300655",
      "name": "晶瑞电材",
      "pct_chg": 4.28,
      "price": 18.53,
      "prev_high": 18.08,
      "prev_high_date": "2026-06-24",
      "turnover": 15.15
    },
    {
      "code": "300666",
      "name": "江丰电子",
      "pct_chg": 7.51,
      "price": 354.78,
      "prev_high": 330.0,
      "prev_high_date": "2026-06-25",
      "turnover": 12.32
    },
    {
      "code": "300668",
      "name": "杰恩股份",
      "pct_chg": 15.66,
      "price": 65.3,
      "prev_high": 63.8,
      "prev_high_date": "2026-06-22",
      "turnover": 13.49
    },
    {
      "code": "300717",
      "name": "华信新材",
      "pct_chg": 8.05,
      "price": 22.0,
      "prev_high": 20.36,
      "prev_high_date": "2026-06-25",
      "turnover": 13.39
    },
    {
      "code": "300720",
      "name": "海川智能",
      "pct_chg": 10.41,
      "price": 88.88,
      "prev_high": 84.5,
      "prev_high_date": "2026-06-17",
      "turnover": 9.5
    },
    {
      "code": "300721",
      "name": "怡达股份",
      "pct_chg": 5.15,
      "price": 36.96,
      "prev_high": 35.83,
      "prev_high_date": "2026-06-10",
      "turnover": 31.7
    },
    {
      "code": "300727",
      "name": "润禾材料",
      "pct_chg": 9.39,
      "price": 38.44,
      "prev_high": 38.13,
      "prev_high_date": "2026-06-17",
      "turnover": 11.37
    },
    {
      "code": "300749",
      "name": "顶固集创",
      "pct_chg": 14.21,
      "price": 27.49,
      "prev_high": 24.07,
      "prev_high_date": "2026-06-25",
      "turnover": 14.28
    },
    {
      "code": "300759",
      "name": "康龙化成",
      "pct_chg": 3.75,
      "price": 26.32,
      "prev_high": 25.5,
      "prev_high_date": "2026-05-26",
      "turnover": 5.41
    },
    {
      "code": "300762",
      "name": "上海瀚讯",
      "pct_chg": 11.89,
      "price": 45.25,
      "prev_high": 41.7,
      "prev_high_date": "2026-06-24",
      "turnover": 13.88
    },
    {
      "code": "300776",
      "name": "帝尔激光",
      "pct_chg": 8.54,
      "price": 194.5,
      "prev_high": 179.2,
      "prev_high_date": "2026-06-25",
      "turnover": 14.09
    },
    {
      "code": "300780",
      "name": "德恩精工",
      "pct_chg": 6.8,
      "price": 33.0,
      "prev_high": 32.32,
      "prev_high_date": "2026-06-16",
      "turnover": 15.61
    },
    {
      "code": "300786",
      "name": "国林科技",
      "pct_chg": 2.42,
      "price": 23.72,
      "prev_high": 23.25,
      "prev_high_date": "2026-06-24",
      "turnover": 14.7
    },
    {
      "code": "300801",
      "name": "泰和科技",
      "pct_chg": 6.89,
      "price": 30.27,
      "prev_high": 28.98,
      "prev_high_date": "2026-06-23",
      "turnover": 15.89
    },
    {
      "code": "300820",
      "name": "英杰电气",
      "pct_chg": 3.45,
      "price": 83.43,
      "prev_high": 80.65,
      "prev_high_date": "2026-06-25",
      "turnover": 7.21
    },
    {
      "code": "300938",
      "name": "信测标准",
      "pct_chg": 4.33,
      "price": 52.51,
      "prev_high": 50.33,
      "prev_high_date": "2026-06-25",
      "turnover": 9.48
    },
    {
      "code": "300985",
      "name": "致远新能",
      "pct_chg": 1.91,
      "price": 36.88,
      "prev_high": 36.19,
      "prev_high_date": "2026-06-25",
      "turnover": 3.25
    },
    {
      "code": "600058",
      "name": "五矿发展",
      "pct_chg": 0.94,
      "price": 11.88,
      "prev_high": 11.77,
      "prev_high_date": "2026-06-25",
      "turnover": 4.28
    },
    {
      "code": "600141",
      "name": "兴发集团",
      "pct_chg": 2.78,
      "price": 48.8,
      "prev_high": 47.48,
      "prev_high_date": "2026-06-25",
      "turnover": 11.69
    },
    {
      "code": "600160",
      "name": "巨化股份",
      "pct_chg": 0.3,
      "price": 50.95,
      "prev_high": 50.8,
      "prev_high_date": "2026-06-25",
      "turnover": 3.71
    },
    {
      "code": "600176",
      "name": "中国巨石",
      "pct_chg": 4.69,
      "price": 74.12,
      "prev_high": 70.8,
      "prev_high_date": "2026-06-25",
      "turnover": 5.67
    },
    {
      "code": "600184",
      "name": "光电股份",
      "pct_chg": 3.56,
      "price": 30.21,
      "prev_high": 29.17,
      "prev_high_date": "2026-06-25",
      "turnover": 14.21
    },
    {
      "code": "600198",
      "name": "大唐电信",
      "pct_chg": 1.88,
      "price": 9.75,
      "prev_high": 9.63,
      "prev_high_date": "2026-06-16",
      "turnover": 6.24
    },
    {
      "code": "600206",
      "name": "有研新材",
      "pct_chg": 8.19,
      "price": 60.76,
      "prev_high": 56.16,
      "prev_high_date": "2026-06-25",
      "turnover": 17.05
    },
    {
      "code": "600228",
      "name": "返利科技",
      "pct_chg": 9.99,
      "price": 10.79,
      "prev_high": 9.81,
      "prev_high_date": "2026-06-25",
      "turnover": 0.14
    },
    {
      "code": "600237",
      "name": "铜峰电子",
      "pct_chg": 1.69,
      "price": 13.21,
      "prev_high": 12.99,
      "prev_high_date": "2026-06-25",
      "turnover": 22.48
    },
    {
      "code": "600246",
      "name": "万通发展",
      "pct_chg": 1.32,
      "price": 19.97,
      "prev_high": 19.71,
      "prev_high_date": "2026-06-25",
      "turnover": 9.26
    },
    {
      "code": "600397",
      "name": "江钨装备",
      "pct_chg": 1.4,
      "price": 26.04,
      "prev_high": 25.68,
      "prev_high_date": "2026-06-25",
      "turnover": 10.23
    },
    {
      "code": "600460",
      "name": "士兰微",
      "pct_chg": 1.04,
      "price": 50.38,
      "prev_high": 50.01,
      "prev_high_date": "2026-06-24",
      "turnover": 11.17
    },
    {
      "code": "600497",
      "name": "驰宏锌锗",
      "pct_chg": 1.87,
      "price": 12.54,
      "prev_high": 12.31,
      "prev_high_date": "2026-06-25",
      "turnover": 8.79
    },
    {
      "code": "600552",
      "name": "凯盛科技",
      "pct_chg": 10.0,
      "price": 29.6,
      "prev_high": 27.85,
      "prev_high_date": "2026-06-24",
      "turnover": 16.23
    },
    {
      "code": "600596",
      "name": "新安股份",
      "pct_chg": 3.79,
      "price": 17.8,
      "prev_high": 17.29,
      "prev_high_date": "2026-06-24",
      "turnover": 9.69
    },
    {
      "code": "600630",
      "name": "龙头股份",
      "pct_chg": 2.85,
      "price": 9.74,
      "prev_high": 9.59,
      "prev_high_date": "2026-06-24",
      "turnover": 10.67
    },
    {
      "code": "600641",
      "name": "先导基电",
      "pct_chg": 2.85,
      "price": 38.26,
      "prev_high": 37.76,
      "prev_high_date": "2026-06-24",
      "turnover": 9.78
    },
    {
      "code": "600667",
      "name": "太极实业",
      "pct_chg": 6.2,
      "price": 26.88,
      "prev_high": 25.31,
      "prev_high_date": "2026-06-25",
      "turnover": 25.24
    },
    {
      "code": "600707",
      "name": "彩虹股份",
      "pct_chg": 2.42,
      "price": 13.96,
      "prev_high": 13.63,
      "prev_high_date": "2026-06-25",
      "turnover": 8.84
    },
    {
      "code": "600770",
      "name": "综艺股份",
      "pct_chg": 5.41,
      "price": 6.82,
      "prev_high": 6.56,
      "prev_high_date": "2026-05-26",
      "turnover": 9.49
    },
    {
      "code": "600857",
      "name": "宁波中百",
      "pct_chg": 2.94,
      "price": 17.87,
      "prev_high": 17.36,
      "prev_high_date": "2026-06-25",
      "turnover": 13.85
    },
    {
      "code": "600877",
      "name": "电科芯片",
      "pct_chg": 0.36,
      "price": 16.7,
      "prev_high": 16.64,
      "prev_high_date": "2026-06-25",
      "turnover": 5.12
    },
    {
      "code": "600888",
      "name": "新疆众和",
      "pct_chg": 0.0,
      "price": 16.12,
      "prev_high": 16.12,
      "prev_high_date": "2026-06-25",
      "turnover": 12.51
    },
    {
      "code": "600909",
      "name": "华安证券",
      "pct_chg": 0.75,
      "price": 12.14,
      "prev_high": 12.05,
      "prev_high_date": "2026-06-25",
      "turnover": 10.07
    },
    {
      "code": "600962",
      "name": "国投中鲁",
      "pct_chg": 10.02,
      "price": 29.0,
      "prev_high": 26.36,
      "prev_high_date": "2026-06-25",
      "turnover": 3.77
    },
    {
      "code": "601066",
      "name": "中信建投",
      "pct_chg": 2.33,
      "price": 30.25,
      "prev_high": 29.56,
      "prev_high_date": "2026-06-25",
      "turnover": 2.25
    },
    {
      "code": "601133",
      "name": "柏诚股份",
      "pct_chg": 10.0,
      "price": 38.28,
      "prev_high": 34.8,
      "prev_high_date": "2026-06-25",
      "turnover": 7.06
    },
    {
      "code": "601636",
      "name": "旗滨集团",
      "pct_chg": 6.95,
      "price": 8.93,
      "prev_high": 8.67,
      "prev_high_date": "2026-06-17",
      "turnover": 12.59
    },
    {
      "code": "603002",
      "name": "宏昌电子",
      "pct_chg": 5.13,
      "price": 26.23,
      "prev_high": 25.94,
      "prev_high_date": "2026-06-22",
      "turnover": 11.84
    },
    {
      "code": "603004",
      "name": "鼎龙科技",
      "pct_chg": 5.32,
      "price": 23.75,
      "prev_high": 22.99,
      "prev_high_date": "2026-06-24",
      "turnover": 16.06
    },
    {
      "code": "603005",
      "name": "晶方科技",
      "pct_chg": 4.62,
      "price": 52.31,
      "prev_high": 50.0,
      "prev_high_date": "2026-06-25",
      "turnover": 18.91
    },
    {
      "code": "603010",
      "name": "万盛股份",
      "pct_chg": 6.95,
      "price": 16.61,
      "prev_high": 15.91,
      "prev_high_date": "2026-05-26",
      "turnover": 9.43
    },
    {
      "code": "603019",
      "name": "中科曙光",
      "pct_chg": 0.96,
      "price": 98.76,
      "prev_high": 97.82,
      "prev_high_date": "2026-06-25",
      "turnover": 10.31
    },
    {
      "code": "603061",
      "name": "金海通",
      "pct_chg": 3.75,
      "price": 415.05,
      "prev_high": 400.05,
      "prev_high_date": "2026-06-25",
      "turnover": 3.65
    },
    {
      "code": "603065",
      "name": "宿迁联盛",
      "pct_chg": 8.54,
      "price": 21.85,
      "prev_high": 20.13,
      "prev_high_date": "2026-06-25",
      "turnover": 14.7
    },
    {
      "code": "603078",
      "name": "江化微",
      "pct_chg": 4.49,
      "price": 47.95,
      "prev_high": 47.28,
      "prev_high_date": "2026-06-17",
      "turnover": 12.34
    },
    {
      "code": "603125",
      "name": "常青科技",
      "pct_chg": 0.36,
      "price": 30.83,
      "prev_high": 30.8,
      "prev_high_date": "2026-06-23",
      "turnover": 2.93
    },
    {
      "code": "603155",
      "name": "新亚强",
      "pct_chg": 9.98,
      "price": 25.34,
      "prev_high": 25.12,
      "prev_high_date": "2026-06-11",
      "turnover": 6.63
    },
    {
      "code": "603156",
      "name": "养元饮品",
      "pct_chg": 2.03,
      "price": 46.69,
      "prev_high": 46.45,
      "prev_high_date": "2026-06-24",
      "turnover": 1.25
    },
    {
      "code": "603163",
      "name": "圣晖集成",
      "pct_chg": 10.0,
      "price": 135.58,
      "prev_high": 123.25,
      "prev_high_date": "2026-06-25",
      "turnover": 3.68
    },
    {
      "code": "603203",
      "name": "快克智能",
      "pct_chg": 3.83,
      "price": 76.0,
      "prev_high": 73.2,
      "prev_high_date": "2026-06-25",
      "turnover": 6.51
    },
    {
      "code": "603223",
      "name": "恒通股份",
      "pct_chg": 0.25,
      "price": 11.99,
      "prev_high": 11.96,
      "prev_high_date": "2026-06-25",
      "turnover": 4.03
    },
    {
      "code": "603256",
      "name": "宏和科技",
      "pct_chg": 7.31,
      "price": 297.0,
      "prev_high": 276.76,
      "prev_high_date": "2026-06-25",
      "turnover": 1.95
    },
    {
      "code": "603259",
      "name": "药明康德",
      "pct_chg": 0.82,
      "price": 118.18,
      "prev_high": 117.22,
      "prev_high_date": "2026-06-25",
      "turnover": 2.77
    },
    {
      "code": "603261",
      "name": "立航科技",
      "pct_chg": 10.0,
      "price": 57.2,
      "prev_high": 52.0,
      "prev_high_date": "2026-06-25",
      "turnover": 2.29
    },
    {
      "code": "603281",
      "name": "江瀚新材",
      "pct_chg": 7.15,
      "price": 42.13,
      "prev_high": 40.64,
      "prev_high_date": "2026-06-24",
      "turnover": 3.08
    },
    {
      "code": "603313",
      "name": "梦百合",
      "pct_chg": 4.83,
      "price": 5.86,
      "prev_high": 5.78,
      "prev_high_date": "2026-06-01",
      "turnover": 8.96
    },
    {
      "code": "603324",
      "name": "盛剑科技",
      "pct_chg": 6.83,
      "price": 51.02,
      "prev_high": 47.76,
      "prev_high_date": "2026-06-25",
      "turnover": 10.06
    },
    {
      "code": "603341",
      "name": "龙旗科技",
      "pct_chg": 1.46,
      "price": 42.55,
      "prev_high": 41.94,
      "prev_high_date": "2026-06-25",
      "turnover": 12.4
    },
    {
      "code": "603380",
      "name": "易德龙",
      "pct_chg": 1.19,
      "price": 45.94,
      "prev_high": 45.4,
      "prev_high_date": "2026-06-25",
      "turnover": 4.95
    },
    {
      "code": "603386",
      "name": "骏亚科技",
      "pct_chg": 3.38,
      "price": 20.78,
      "prev_high": 20.25,
      "prev_high_date": "2026-06-24",
      "turnover": 12.86
    },
    {
      "code": "603444",
      "name": "吉比特",
      "pct_chg": 1.5,
      "price": 351.15,
      "prev_high": 345.96,
      "prev_high_date": "2026-06-25",
      "turnover": 3.9
    },
    {
      "code": "603458",
      "name": "勘设股份",
      "pct_chg": 0.78,
      "price": 15.41,
      "prev_high": 15.29,
      "prev_high_date": "2026-06-25",
      "turnover": 14.09
    },
    {
      "code": "603595",
      "name": "ST东尼",
      "pct_chg": 5.0,
      "price": 36.98,
      "prev_high": 35.22,
      "prev_high_date": "2026-06-25",
      "turnover": 1.45
    },
    {
      "code": "603650",
      "name": "彤程新材",
      "pct_chg": 10.0,
      "price": 85.83,
      "prev_high": 78.03,
      "prev_high_date": "2026-06-25",
      "turnover": 5.84
    },
    {
      "code": "603661",
      "name": "恒林股份",
      "pct_chg": 7.4,
      "price": 40.06,
      "prev_high": 37.47,
      "prev_high_date": "2026-05-26",
      "turnover": 10.25
    },
    {
      "code": "603668",
      "name": "天马科技",
      "pct_chg": 3.27,
      "price": 12.32,
      "prev_high": 12.26,
      "prev_high_date": "2026-06-23",
      "turnover": 3.27
    },
    {
      "code": "603678",
      "name": "火炬电子",
      "pct_chg": 5.8,
      "price": 79.49,
      "prev_high": 75.13,
      "prev_high_date": "2026-06-25",
      "turnover": 12.13
    },
    {
      "code": "603688",
      "name": "石英股份",
      "pct_chg": 3.64,
      "price": 86.6,
      "prev_high": 86.1,
      "prev_high_date": "2026-06-22",
      "turnover": 7.75
    },
    {
      "code": "603690",
      "name": "至纯科技",
      "pct_chg": 2.66,
      "price": 35.49,
      "prev_high": 34.57,
      "prev_high_date": "2026-06-25",
      "turnover": 21.29
    },
    {
      "code": "603698",
      "name": "航天工程",
      "pct_chg": 10.0,
      "price": 43.55,
      "prev_high": 39.59,
      "prev_high_date": "2026-06-25",
      "turnover": 6.09
    },
    {
      "code": "603713",
      "name": "密尔克卫",
      "pct_chg": 0.49,
      "price": 76.02,
      "prev_high": 75.65,
      "prev_high_date": "2026-06-25",
      "turnover": 6.01
    },
    {
      "code": "603757",
      "name": "大元泵业",
      "pct_chg": 3.2,
      "price": 74.22,
      "prev_high": 73.7,
      "prev_high_date": "2026-06-24",
      "turnover": 11.26
    },
    {
      "code": "603773",
      "name": "沃格光电",
      "pct_chg": 3.49,
      "price": 178.0,
      "prev_high": 172.15,
      "prev_high_date": "2026-06-23",
      "turnover": 13.94
    },
    {
      "code": "603800",
      "name": "洪田股份",
      "pct_chg": 4.13,
      "price": 88.46,
      "prev_high": 84.95,
      "prev_high_date": "2026-06-25",
      "turnover": 7.32
    },
    {
      "code": "603898",
      "name": "好莱客",
      "pct_chg": 0.69,
      "price": 14.51,
      "prev_high": 14.41,
      "prev_high_date": "2026-06-25",
      "turnover": 3.85
    },
    {
      "code": "603903",
      "name": "中持股份",
      "pct_chg": 10.03,
      "price": 12.84,
      "prev_high": 12.36,
      "prev_high_date": "2026-06-05",
      "turnover": 6.15
    },
    {
      "code": "603929",
      "name": "亚翔集成",
      "pct_chg": 2.27,
      "price": 260.85,
      "prev_high": 255.07,
      "prev_high_date": "2026-06-25",
      "turnover": 6.58
    },
    {
      "code": "603938",
      "name": "三孚股份",
      "pct_chg": 8.8,
      "price": 75.81,
      "prev_high": 71.63,
      "prev_high_date": "2026-06-24",
      "turnover": 12.0
    },
    {
      "code": "603989",
      "name": "艾华集团",
      "pct_chg": 4.19,
      "price": 56.0,
      "prev_high": 53.75,
      "prev_high_date": "2026-06-25",
      "turnover": 9.43
    },
    {
      "code": "605020",
      "name": "永和股份",
      "pct_chg": 6.02,
      "price": 41.22,
      "prev_high": 39.18,
      "prev_high_date": "2026-06-24",
      "turnover": 9.38
    },
    {
      "code": "605111",
      "name": "新洁能",
      "pct_chg": 2.85,
      "price": 83.13,
      "prev_high": 80.83,
      "prev_high_date": "2026-06-25",
      "turnover": 7.76
    },
    {
      "code": "605178",
      "name": "时空科技",
      "pct_chg": 2.47,
      "price": 88.5,
      "prev_high": 86.37,
      "prev_high_date": "2026-06-25",
      "turnover": 8.84
    },
    {
      "code": "605358",
      "name": "立昂微",
      "pct_chg": 6.91,
      "price": 75.37,
      "prev_high": 73.5,
      "prev_high_date": "2026-06-10",
      "turnover": 17.22
    },
    {
      "code": "605366",
      "name": "宏柏新材",
      "pct_chg": 10.02,
      "price": 14.38,
      "prev_high": 13.07,
      "prev_high_date": "2026-06-25",
      "turnover": 19.59
    },
    {
      "code": "605376",
      "name": "博迁新材",
      "pct_chg": 6.95,
      "price": 264.0,
      "prev_high": 246.84,
      "prev_high_date": "2026-06-25",
      "turnover": 7.64
    }
  ],
  "note": "数据源: akshare stock_rank_cxg_ths(), 板块分析需neodata支持"
}